Workbook

Sheet Dashboard
A1: MONTHLY BUDGET DASHBOARD
A4: Month / Year | B4: January 2026
A6: SUMMARY
A7: Total Income | B7: =Income!C8 | D7: Net Savings (Actual) | E7: =B7-B9
A8: Total Budgeted Expenses | B8: =Expenses!B15 | D8: Savings Rate | E8: =IFERROR(E7/B7,0)
A9: Total Actual Expenses | B9: =Expenses!C15 | D9: Status | E9: =IF(E7<0,"OVERSPENT","ON TRACK")
A11: HOW TO USE THIS WORKBOOK
A12: 1. Enter your income sources on the 'Income' tab (planned vs actual).
A13: 2. Enter your budgeted amount per expense category on the 'Expenses' tab.
A14: 3. Log actual spending as it happens on 'Expenses' and 'Daily Transactions'.
A15: 4. Come back to this Dashboard anytime for your at-a-glance summary.

Sheet Income
A1: INCOME
A3: Source | B3: Planned | C3: Actual | D3: Difference
A4: Salary / Wages | B4: 0 | C4: 0 | D4: =C4-B4
A5: Freelance / Side Income | B5: 0 | C5: 0 | D5: =C5-B5
A6: Investments | B6: 0 | C6: 0 | D6: =C6-B6
A7: Other Income | B7: 0 | C7: 0 | D7: =C7-B7
A8: TOTAL | B8: =SUM(B4:B7) | C8: =SUM(C4:C7) | D8: =SUM(D4:D7)

Sheet Expenses
A1: EXPENSES
A3: Category | B3: Budgeted | C3: Actual | D3: Difference | E3: % of Income
A4: Housing / Rent | B4: 0 | C4: 0 | D4: =B4-C4 | E4: =IFERROR(C4/Income!$C$8,0)
A5: Utilities | B5: 0 | C5: 0 | D5: =B5-C5 | E5: =IFERROR(C5/Income!$C$8,0)
A6: Groceries | B6: 0 | C6: 0 | D6: =B6-C6 | E6: =IFERROR(C6/Income!$C$8,0)
A7: Transportation | B7: 0 | C7: 0 | D7: =B7-C7 | E7: =IFERROR(C7/Income!$C$8,0)
A8: Insurance | B8: 0 | C8: 0 | D8: =B8-C8 | E8: =IFERROR(C8/Income!$C$8,0)
A9: Debt Payments | B9: 0 | C9: 0 | D9: =B9-C9 | E9: =IFERROR(C9/Income!$C$8,0)
A10: Subscriptions | B10: 0 | C10: 0 | D10: =B10-C10 | E10: =IFERROR(C10/Income!$C$8,0)
A11: Entertainment | B11: 0 | C11: 0 | D11: =B11-C11 | E11: =IFERROR(C11/Income!$C$8,0)
A12: Personal Care | B12: 0 | C12: 0 | D12: =B12-C12 | E12: =IFERROR(C12/Income!$C$8,0)
A13: Savings & Investments | B13: 0 | C13: 0 | D13: =B13-C13 | E13: =IFERROR(C13/Income!$C$8,0)
A14: Miscellaneous | B14: 0 | C14: 0 | D14: =B14-C14 | E14: =IFERROR(C14/Income!$C$8,0)
A15: TOTAL | B15: =SUM(B4:B14) | C15: =SUM(C4:C14) | D15: =SUM(D4:D14) | E15: =SUM(E4:E14)

Sheet Daily Transactions
A1: DAILY TRANSACTIONS
A3: Date | B3: Type | C3: Category | D3: Description | E3: Amount | F3: Running Balance
F4: =SUM($E$4:E4)
F5: =SUM($E$4:E5)
F6: =SUM($E$4:E6)
F7: =SUM($E$4:E7)
F8: =SUM($E$4:E8)
F9: =SUM($E$4:E9)
F10: =SUM($E$4:E10)
F11: =SUM($E$4:E11)
F12: =SUM($E$4:E12)
F13: =SUM($E$4:E13)
F14: =SUM($E$4:E14)
F15: =SUM($E$4:E15)
... F63: =SUM($E$4:E63)
