Workbook

Sheet Overview
A1: ✈ TRAVEL BUDGET PLANNER
A4: TRIP DETAILS
A5: Trip Name | B5: Summer in Portugal | D5: Trip Length (days) | E5: =IF(AND(B8<>"",B7<>""),B8-B7+1,"")
A6: Destination(s) | B6: Lisbon, Porto | D6: Total Trip Budget | E6: 2000
A7: Start Date | D7: Total Planned (all categories) | E7: ='Budget by Category'!B13
A8: End Date | D8: Total Actual Spent | E8: ='Budget by Category'!C13
A9: Number of Travelers | B9: 2 | D9: Remaining Budget | E9: =E6-E8
A11: TRIP STATUS
A12: Budget Used | B12: =IFERROR(E8/E6,0) | D12: Status | E12: =IF(E9<0,"OVER BUDGET","ON TRACK")
A13: Cost per Traveler | B13: =IFERROR(E8/B9,0)
A14: Cost per Day | B14: =IFERROR(E8/E5,0)
A16: How to use this planner
A17: 1. Fill in your trip details above and set your total budget.
A18: 2. Go to 'Budget by Category' and enter what you plan to spend per category.
A19: 3. Log every purchase in 'Daily Expense Log' as you spend — totals update automatically.
A20: 4. Check back here anytime to see if you're on track.

Sheet Budget by Category
A1: BUDGET BY CATEGORY
A3: Category | B3: Planned | C3: Actual | D3: Difference | E3: % of Total Budget
A4: Flights | B4: 0 | C4: 0 | D4: =B4-C4 | E4: =IFERROR(C4/Overview!$E$6,0)
A5: Lodging / Hotels | B5: 0 | C5: 0 | D5: =B5-C5 | E5: =IFERROR(C5/Overview!$E$6,0)
A6: Food & Dining | B6: 0 | C6: 0 | D6: =B6-C6 | E6: =IFERROR(C6/Overview!$E$6,0)
A7: Local Transportation | B7: 0 | C7: 0 | D7: =B7-C7 | E7: =IFERROR(C7/Overview!$E$6,0)
A8: Activities & Tours | B8: 0 | C8: 0 | D8: =B8-C8 | E8: =IFERROR(C8/Overview!$E$6,0)
A9: Shopping & Souvenirs | B9: 0 | C9: 0 | D9: =B9-C9 | E9: =IFERROR(C9/Overview!$E$6,0)
A10: Travel Insurance | B10: 0 | C10: 0 | D10: =B10-C10 | E10: =IFERROR(C10/Overview!$E$6,0)
A11: Visa / Documents | B11: 0 | C11: 0 | D11: =B11-C11 | E11: =IFERROR(C11/Overview!$E$6,0)
A12: Miscellaneous | B12: 0 | C12: 0 | D12: =B12-C12 | E12: =IFERROR(C12/Overview!$E$6,0)
A13: TOTAL | B13: =SUM(B4:B12) | C13: =SUM(C4:C12) | D13: =SUM(D4:D12) | E13: =SUM(E4:E12)

Sheet Daily Expense Log
A1: DAILY EXPENSE LOG
A3: Date | B3: Category | C3: Description | D3: Payment Method | E3: Amount | F3: Running Total
F4: =SUM($E$4:E4)
F5: =SUM($E$4:E5)
F6: =SUM($E$4:E6)
F7: =SUM($E$4:E7)
F8: =SUM($E$4:E8)
F9: =SUM($E$4:E9)
F10: =SUM($E$4:E10)
F11: =SUM($E$4:E11)
F12: =SUM($E$4:E12)
F13: =SUM($E$4:E13)
F14: =SUM($E$4:E14)
F15: =SUM($E$4:E15)
... F63: =SUM($E$4:E63)
